py_gitea_opensuse_org/__init__.py
py_gitea_opensuse_org/api_client.py
py_gitea_opensuse_org/api_response.py
py_gitea_opensuse_org/configuration.py
py_gitea_opensuse_org/exceptions.py
py_gitea_opensuse_org/py.typed
py_gitea_opensuse_org/rest.py
py_gitea_opensuse_org/api/__init__.py
py_gitea_opensuse_org/api/activitypub_api.py
py_gitea_opensuse_org/api/admin_api.py
py_gitea_opensuse_org/api/issue_api.py
py_gitea_opensuse_org/api/miscellaneous_api.py
py_gitea_opensuse_org/api/notification_api.py
py_gitea_opensuse_org/api/organization_api.py
py_gitea_opensuse_org/api/package_api.py
py_gitea_opensuse_org/api/repository_api.py
py_gitea_opensuse_org/api/settings_api.py
py_gitea_opensuse_org/api/user_api.py
py_gitea_opensuse_org/models/__init__.py
py_gitea_opensuse_org/models/access_token.py
py_gitea_opensuse_org/models/action_artifact.py
py_gitea_opensuse_org/models/action_artifacts_response.py
py_gitea_opensuse_org/models/action_runner.py
py_gitea_opensuse_org/models/action_runner_label.py
py_gitea_opensuse_org/models/action_runners_response.py
py_gitea_opensuse_org/models/action_task.py
py_gitea_opensuse_org/models/action_task_response.py
py_gitea_opensuse_org/models/action_variable.py
py_gitea_opensuse_org/models/action_workflow.py
py_gitea_opensuse_org/models/action_workflow_job.py
py_gitea_opensuse_org/models/action_workflow_jobs_response.py
py_gitea_opensuse_org/models/action_workflow_response.py
py_gitea_opensuse_org/models/action_workflow_run.py
py_gitea_opensuse_org/models/action_workflow_runs_response.py
py_gitea_opensuse_org/models/action_workflow_step.py
py_gitea_opensuse_org/models/activity.py
py_gitea_opensuse_org/models/activity_pub.py
py_gitea_opensuse_org/models/add_collaborator_option.py
py_gitea_opensuse_org/models/add_time_option.py
py_gitea_opensuse_org/models/annotated_tag.py
py_gitea_opensuse_org/models/annotated_tag_object.py
py_gitea_opensuse_org/models/api_error.py
py_gitea_opensuse_org/models/apply_diff_patch_file_options.py
py_gitea_opensuse_org-1.25.2.dist-info/METADATA
py_gitea_opensuse_org-1.25.2.dist-info/WHEEL
py_gitea_opensuse_org-1.25.2.dist-info/top_level.txt
py_gitea_opensuse_org-1.25.2.dist-info/RECORD
