Metadata-Version: 2.4
Name: py_gitea_opensuse_org
Version: 1.25.2
Summary: Gitea API
Author-email: OpenAPI Generator Community <team@openapitools.org>
License: MIT
Project-URL: Repository, https://github.com/dcermak/py-gitea-opensuse-org
Keywords: OpenAPI,OpenAPI-Generator,Gitea API
Requires-Python: >=3.9
Requires-Dist: python-dateutil>=2.8.2
Requires-Dist: aiohttp>=3.8.4
Requires-Dist: aiohttp-retry>=2.8.3
Requires-Dist: pydantic>=2
Requires-Dist: typing-extensions>=4.7.1
